PyMICE-1.2.1.dist-info/DESCRIPTION.rst
PyMICE-1.2.1.dist-info/METADATA
PyMICE-1.2.1.dist-info/RECORD
PyMICE-1.2.1.dist-info/WHEEL
PyMICE-1.2.1.dist-info/metadata.json
PyMICE-1.2.1.dist-info/top_level.txt
pymice/Data.py
pymice/ICFixer.py
pymice/ICNodes.py
pymice/LogAnalyser.py
pymice/_Analysis.py
pymice/_Bibliography.py
pymice/_C.pyd
pymice/_Debug.py
pymice/_Ens.py
pymice/_FixTimezones.py
pymice/_FixTimezonesTest.py
pymice/_GetTutorialData.py
pymice/_ICData.py
pymice/_ICNodes2.py
pymice/_ICNodes3.py
pymice/_ICNodesBase.py
pymice/_Metadata.py
pymice/_ObjectBase.py
pymice/_Results.py
pymice/_Tools.py
pymice/_Version.py
pymice/__init__.py
pymice/debug.py
pymice/_Python2/ICNodes.py
pymice/_Python2/Tools.py
pymice/_Python2/__init__.py
pymice/_Python3/ICNodes.py
pymice/_Python3/Tools.py
pymice/_Python3/__init__.py
pymice/data/tutorial/COPYING
pymice/data/tutorial/LICENSE
pymice/data/tutorial/demo.zip
pymice/data/tutorial/C57_AB/2012-08-28 13.44.51.zip
pymice/data/tutorial/C57_AB/2012-08-28 15.33.58.zip
pymice/data/tutorial/C57_AB/2012-08-31 11.46.31.zip
pymice/data/tutorial/C57_AB/2012-08-31 11.58.22.zip
pymice/data/tutorial/C57_AB/COPYING
pymice/data/tutorial/C57_AB/LICENSE
pymice/data/tutorial/C57_AB/timeline.ini
pymice/data/tutorial/FVB/2016-07-20 10.11.11.zip
pymice/data/tutorial/FVB/COPYING
pymice/data/tutorial/FVB/LICENSE
pymice/data/tutorial/FVB/timeline.ini
