Metadata-Version: 2.0
Name: PyMICE
Version: 1.2.1
Summary: PyMICE - a Python® library for mice behavioural data analysis
Home-page: https://neuroinflab.wordpress.com/research/pymice/
Author: Jakub M. Dzik a.k.a. Kowalski, S. Leski (Laboratory of Neuroinformatics; Nencki Institute of Experimental Biology)
Author-email: jakub.m.dzik+pymice@gmail.com, sz.leski+pymice@gmail.com
License: GPL3
Keywords: IntelliCage mice behavioural data loading analysis
Platform: UNKNOWN
Classifier: Development Status :: 5 - Production/Stable
Classifier: Intended Audience :: Developers
Classifier: Intended Audience :: Science/Research
Classifier: License :: OSI Approved :: GNU General Public License v3 (GPLv3)
Classifier: Natural Language :: English
Classifier: Operating System :: OS Independent
Classifier: Programming Language :: C
Classifier: Programming Language :: Python
Classifier: Programming Language :: Python :: 2
Classifier: Programming Language :: Python :: 2.7
Classifier: Programming Language :: Python :: 3
Classifier: Programming Language :: Python :: 3.3
Classifier: Programming Language :: Python :: 3.4
Classifier: Programming Language :: Python :: 3.5
Classifier: Programming Language :: Python :: 3.6
Classifier: Topic :: Scientific/Engineering
Classifier: Topic :: Scientific/Engineering :: Bio-Informatics
Classifier: Topic :: Software Development
Classifier: Topic :: Software Development :: Libraries :: Python Modules
Requires: dateutil
Requires: matplotlib
Requires: numpy
Requires: pytz
